chess_ng/__init__.py
chess_ng/__main__.py
chess_ng/algorithm.py
chess_ng/board.py
chess_ng/cli.py
chess_ng/consts.py
chess_ng/fen.py
chess_ng/game.py
chess_ng/hashing.py
chess_ng/interfaces.py
chess_ng/move.py
chess_ng/output.py
chess_ng/piece.py
chess_ng/renderer.py
chess_ng/team.py
chess_ng/util.py
chess_ng-1.1.1.dist-info/LICENSE
chess_ng-1.1.1.dist-info/METADATA
chess_ng-1.1.1.dist-info/WHEEL
chess_ng-1.1.1.dist-info/top_level.txt
chess_ng-1.1.1.dist-info/RECORD
