Metadata-Version: 2.1
Name: chess_ng
Version: 1.1.1
Summary: Chess engine including minimax AI
Home-page: https://github.com/rbaltrusch/chess_ng
Author: Richard Baltrusch
License: MIT
Keywords: python
Classifier: Development Status :: 4 - Beta
Classifier: Intended Audience :: Developers
Classifier: License :: OSI Approved :: MIT License
Classifier: Programming Language :: Python
Classifier: Programming Language :: Python :: 3
Classifier: Programming Language :: Python :: 3 :: Only
Classifier: Programming Language :: Python :: 3.8
Classifier: Programming Language :: Python :: 3.9
Classifier: Programming Language :: Python :: 3.10
Classifier: Programming Language :: Python :: 3.11
Classifier: Topic :: Games/Entertainment
Classifier: Topic :: Games/Entertainment :: Board Games
Classifier: Topic :: Games/Entertainment :: Simulation
Classifier: Topic :: Scientific/Engineering :: Artificial Intelligence
Classifier: Environment :: Console
Classifier: Typing :: Typed
Requires-Python: >=3.8
License-File: LICENSE
Requires-Dist: colorama ==0.4.5
Requires-Dist: numpy ==1.24.0
Requires-Dist: Pillow ==10.0.1
